ffmpeg_smart_trim/__init__.py
ffmpeg_smart_trim/trim.py
ffmpeg_smart_trim-0.0.3.dist-info/LICENSE
ffmpeg_smart_trim-0.0.3.dist-info/METADATA
ffmpeg_smart_trim-0.0.3.dist-info/WHEEL
ffmpeg_smart_trim-0.0.3.dist-info/top_level.txt
ffmpeg_smart_trim-0.0.3.dist-info/RECORD
