Metadata-Version: 2.1
Name: ffmpeg-smart-trim
Version: 0.0.3
Summary: Smart trim with FFMPEG
Home-page: https://github.com/valkjsaaa/ffmpeg-smart-trim
Author: Jackie Yang
Author-email: jackie@jackieyang.me
Project-URL: Bug Tracker, https://github.com/valkjsaaa/ffmpeg-smart-trim/issues
Classifier: Development Status :: 3 - Alpha
Classifier: Programming Language :: Python :: 3
Classifier: License :: OSI Approved :: GNU General Public License v3 (GPLv3)
Classifier: Operating System :: OS Independent
Requires-Python: >=3.7
License-File: LICENSE
Requires-Dist: ffmpeg-python
